pygments_openssl/__init__.py
pygments_openssl/lexer.py
pygments_openssl-1.6.dist-info/LICENSE
pygments_openssl-1.6.dist-info/METADATA
pygments_openssl-1.6.dist-info/WHEEL
pygments_openssl-1.6.dist-info/entry_points.txt
pygments_openssl-1.6.dist-info/top_level.txt
pygments_openssl-1.6.dist-info/RECORD
