Metadata-Version: 2.1
Name: pygments-openssl
Version: 1.6
Summary: Syntax coloring for OpenSSL configuration files
Home-page: https://github.com/stefanholek/pygments-openssl
Author: Stefan H. Holek
Author-email: stefan@epy.co.at
License: BSD-2-Clause
Keywords: sphinx,pygments,lexer,openssl,openssl.cnf,openssl.conf,syntax,coloring,colors,highlight
Classifier: Development Status :: 5 - Production/Stable
Classifier: Environment :: Plugins
Classifier: Intended Audience :: Developers
Classifier: Intended Audience :: End Users/Desktop
Classifier: Intended Audience :: System Administrators
Classifier: License :: OSI Approved :: BSD License
Classifier: Operating System :: OS Independent
Classifier: Programming Language :: Python
Classifier: Programming Language :: Python :: 2
Classifier: Programming Language :: Python :: 3
Classifier: Topic :: Text Processing :: Filters
Requires-Python: !=3.0.*,!=3.1.*,!=3.2.*,!=3.3.*,>=2.7
License-File: LICENSE
Requires-Dist: setuptools
Requires-Dist: pygments
